odoo/addons/sale_report_commitment_date/README.rst
odoo/addons/sale_report_commitment_date/__init__.py
odoo/addons/sale_report_commitment_date/__manifest__.py
odoo/addons/sale_report_commitment_date/i18n/es.po
odoo/addons/sale_report_commitment_date/i18n/fr.po
odoo/addons/sale_report_commitment_date/i18n/it.po
odoo/addons/sale_report_commitment_date/i18n/sale_report_commitment_date.pot
odoo/addons/sale_report_commitment_date/readme/CONTRIBUTORS.rst
odoo/addons/sale_report_commitment_date/readme/DESCRIPTION.rst
odoo/addons/sale_report_commitment_date/reports/__init__.py
odoo/addons/sale_report_commitment_date/reports/sale_report.py
odoo/addons/sale_report_commitment_date/reports/sale_report.xml
odoo/addons/sale_report_commitment_date/static/description/icon.png
odoo/addons/sale_report_commitment_date/static/description/index.html
odoo14_addon_sale_report_commitment_date-14.0.1.0.1.dev7.dist-info/METADATA
odoo14_addon_sale_report_commitment_date-14.0.1.0.1.dev7.dist-info/WHEEL
odoo14_addon_sale_report_commitment_date-14.0.1.0.1.dev7.dist-info/top_level.txt
odoo14_addon_sale_report_commitment_date-14.0.1.0.1.dev7.dist-info/RECORD
